perdiem/__init__.py
perdiem/main.py
perdiem/perdiem.db
perdiem-0.1.2.dist-info/METADATA
perdiem-0.1.2.dist-info/WHEEL
perdiem-0.1.2.dist-info/RECORD
