Metadata-Version: 2.1
Name: perdiem
Version: 0.1.2
Summary: A simple per diem library
Author: V. David Zvenyach
Author-email: dave@zvenyach.com
Requires-Python: >=3.11,<4.0
Classifier: Programming Language :: Python :: 3
Classifier: Programming Language :: Python :: 3.11
Classifier: Programming Language :: Python :: 3.12
